sample_finder/__init__.py
sample_finder/app.py
sample_finder/validators.py
sample_finder/sources/__init__.py
sample_finder/sources/malpedia.py
sample_finder/sources/malshare.py
sample_finder/sources/malwarebazaar.py
sample_finder/sources/mwdb.py
sample_finder/sources/source.py
sample_finder/sources/triage.py
sample_finder/sources/virusexchange.py
sample_finder/sources/virusshare.py
sample_finder/sources/virustotal.py
sample_finder-1.0.0.16.dist-info/METADATA
sample_finder-1.0.0.16.dist-info/WHEEL
sample_finder-1.0.0.16.dist-info/entry_points.txt
sample_finder-1.0.0.16.dist-info/RECORD
