Metadata-Version: 2.4
Name: sample-finder
Version: 1.0.0.16
Summary: Sample Finder is a modular tool to search for and download malware samples from public malware sources.
Project-URL: Homepage, https://github.com/joren485/sample-finder
Requires-Python: >=3.11
Requires-Dist: loguru>=0.7.3
Requires-Dist: pyyaml>=6.0.2
Requires-Dist: pyzipper>=0.3.6
Requires-Dist: requests>=2.32.3
Requires-Dist: typer>=0.15.4
